<Ui xmlns="http://www.blizzard.com/wow/ui/" xmlns:xsi="http://www.w3.org/2001/XMLSchema-instance" xsi:schemaLocation="http://www.blizzard.com/wow/ui/..\FrameXML\UI.xsd">
	<Include file="mainFrame.lua"/>
	<Include file="profileTable/actionButton.lua"/>
	<Include file="profileTable/profileTable.lua"/>
	<Include file="intro/introFrame.lua"/>
	<Include file="intro/welcomePage.lua"/>
	<Include file="intro/resolutionPage.lua"/>
	<Include file="intro/directProfilesPage.lua"/>
	<Include file="intro/indirectProfilesPage.lua"/>
	<Include file="intro/weakaurasPage.lua"/>
	<Include file="intro/donePage.lua"/>
</Ui>
